README.md
gorep.py
setup.py
gorep.egg-info/PKG-INFO
gorep.egg-info/SOURCES.txt
gorep.egg-info/dependency_links.txt
gorep.egg-info/entry_points.txt
gorep.egg-info/top_level.txt