Metadata-Version: 2.1
Name: gorep
Version: 0.1.1
Summary: Gor Grep Middleware.
Home-page: https://github.com/huyx/gorep
Author: ycyuxin
Author-email: ycyuxin@qq.com
License: UNKNOWN
Platform: UNKNOWN
